git_star_percentile/__init__.py
git_star_percentile/__main__.py
git_star_percentile-1.8.dist-info/LICENSE
git_star_percentile-1.8.dist-info/METADATA
git_star_percentile-1.8.dist-info/WHEEL
git_star_percentile-1.8.dist-info/entry_points.txt
git_star_percentile-1.8.dist-info/top_level.txt
git_star_percentile-1.8.dist-info/RECORD
