Metadata-Version: 2.1
Name: git-star-percentile
Version: 1.8
Summary: A simple tool to quantify your GitHub repo star percentile.
Home-page: https://github.com/ChenLiu-1996/GitStarPercentile
Author: Chen Liu
Author-email: chen.liu.cl2482@yale.edu
License: MIT
Keywords: GitHub,repository,star,popularity,percentile
Classifier: Development Status :: 3 - Alpha
Classifier: Intended Audience :: Developers
Classifier: License :: OSI Approved :: MIT License
Classifier: Programming Language :: Python :: 3
License-File: LICENSE
Requires-Dist: pandas
Requires-Dist: requests
